piargus/__init__.py
piargus/batchwriter.py
piargus/constants.py
piargus/helpers.py
piargus/job.py
piargus/tauargus.py
piargus/inputspec/__init__.py
piargus/inputspec/codelist.py
piargus/inputspec/inputdata.py
piargus/inputspec/metadata.py
piargus/inputspec/microdata.py
piargus/inputspec/tabledata.py
piargus/inputspec/hierarchy/__init__.py
piargus/inputspec/hierarchy/flathierarchy.py
piargus/inputspec/hierarchy/hierarchy.py
piargus/inputspec/hierarchy/hrcserializer.py
piargus/inputspec/hierarchy/levelhierarchy.py
piargus/inputspec/hierarchy/treehierarchy.py
piargus/outputspec/__init__.py
piargus/outputspec/apriori.py
piargus/outputspec/safetyrule.py
piargus/outputspec/table.py
piargus/outputspec/treerecode.py
piargus/result/__init__.py
piargus/result/argusreport.py
piargus/result/tableresult.py
piargus-1.0.3.dist-info/LICENSE
piargus-1.0.3.dist-info/METADATA
piargus-1.0.3.dist-info/WHEEL
piargus-1.0.3.dist-info/top_level.txt
piargus-1.0.3.dist-info/RECORD
