Metadata-Version: 2.2
Name: piargus
Version: 1.0.3
Summary: Python wrapper around TauArgus
Author-email: lverweijen <lauwerund@gmail.com>
License: Apache License 2.0
Project-URL: Homepage, https://github.com/lverweijen/piargus
Project-URL: Repository, https://github.com/lverweijen/piargus
Project-URL: Documentation, https://lverweijen.github.io/piargus
Project-URL: Issues, https://github.com/lverweijen/piargus/issues
Project-URL: Changelog, https://lverweijen.github.io/piargus/changes.html
Keywords: statistical-disclosure-control,tau-argus
Classifier: Intended Audience :: Developers
Classifier: Intended Audience :: Science/Research
Classifier: Operating System :: Microsoft :: Windows
Classifier: License :: OSI Approved :: Apache Software License
Classifier: Programming Language :: Python :: 3
Classifier: Programming Language :: Python :: 3.9
Classifier: Programming Language :: Python :: 3.10
Classifier: Programming Language :: Python :: 3.11
Classifier: Programming Language :: Python :: 3.12
Classifier: Programming Language :: Python :: 3.13
Classifier: Typing :: Typed
Requires-Python: >=3.9
License-File: LICENSE
Requires-Dist: littletree>=0.6.2
Requires-Dist: pandas>=1.5
Provides-Extra: export
Requires-Dist: Pillow>=5.0; extra == "export"
Requires-Dist: matplotlib>=3.0; extra == "export"
Requires-Dist: svglib>=1.5.0; extra == "export"
